rfc6920/__init__.py
rfc6920/methods.py
rfc6920/py.typed
rfc6920-0.2.2.dist-info/LICENSE.txt
rfc6920-0.2.2.dist-info/METADATA
rfc6920-0.2.2.dist-info/WHEEL
rfc6920-0.2.2.dist-info/top_level.txt
rfc6920-0.2.2.dist-info/RECORD
