Metadata-Version: 2.1
Name: rfc6920
Version: 0.2.2
Summary: A library to generate and validate RFC6920 URIs
Home-page: https://github.com/inab/pyrfc6920
Author: José M. Fernández <https://orcid.org/0000-0002-4806-5140>
Author-email: jose.m.fernandez@bsc.es
License: LGPL-2.1
Project-URL: Bug Tracker, https://github.com/inab/pyrfc6920/issues
Classifier: Programming Language :: Python :: 3
Classifier: Development Status :: 3 - Alpha
Classifier: License :: OSI Approved :: GNU Lesser General Public License v2 or later (LGPLv2+)
Classifier: Operating System :: OS Independent
Requires-Python: >=3.6
License-File: LICENSE.txt
Requires-Dist: genluhn (>=0.3.1)
